jsonasobj/__init__.py
jsonasobj/extendednamespace.py
jsonasobj/jsonobj.py
jsonasobj-2.0.1.dist-info/AUTHORS
jsonasobj-2.0.1.dist-info/METADATA
jsonasobj-2.0.1.dist-info/WHEEL
jsonasobj-2.0.1.dist-info/pbr.json
jsonasobj-2.0.1.dist-info/top_level.txt
jsonasobj-2.0.1.dist-info/RECORD
