Metadata-Version: 1.2
Name: jsonasobj
Version: 2.0.1
Summary: JSON as python objects
Home-page: https://github.com/hsolbrig/jsonasobj
Author: Harold Solbrig
Author-email: solbrig@jhu.edu
License: CC0 1.0 Universal
Keywords: linkml,LOD,Modeling,Linked open data,model
Platform: UNKNOWN
Classifier: Development Status :: 5 - Production/Stable
Classifier: Environment :: Web Environment
Classifier: Intended Audience :: Developers
Classifier: License :: CC0 1.0 Universal (CC0 1.0) Public Domain Dedication
Classifier: Operating System :: OS Independent
Classifier: Programming Language :: Python
Classifier: Topic :: Software Development :: Libraries
Classifier: Programming Language :: Python :: 3 :: Only
Classifier: Programming Language :: Python :: 3.6
Classifier: Programming Language :: Python :: 3.7
Classifier: Programming Language :: Python :: 3.8
Classifier: Programming Language :: Python :: 3.9
Requires-Python: >=3.6
